{"game_id": "a47fe46f-cfd1-4be3-ad75-d7dbbd5eacb3", "score": 100, "timestamp": "2026-03-18T11:20:11.269056", "row": 6, "column": 5, "message": "Game started with specified height and width.", "height": 10, "width": 10, "type": "GameStartedEvent"}
{"game_id": "a47fe46f-cfd1-4be3-ad75-d7dbbd5eacb3", "score": 99, "timestamp": "2026-03-18T11:20:17.056982", "row": 5, "column": 5, "message": "You moved in the specified direction.", "direction": "N", "type": "PlayerMovedEvent"}
{"game_id": "a47fe46f-cfd1-4be3-ad75-d7dbbd5eacb3", "score": 98, "timestamp": "2026-03-18T11:20:27.670448", "row": 4, "column": 5, "message": "You moved in the specified direction.", "direction": "N", "type": "PlayerMovedEvent"}
{"game_id": "a47fe46f-cfd1-4be3-ad75-d7dbbd5eacb3", "score": 97, "timestamp": "2026-03-18T11:20:31.995356", "row": 3, "column": 5, "message": "You moved in the specified direction.", "direction": "N", "type": "PlayerMovedEvent"}
{"game_id": "a47fe46f-cfd1-4be3-ad75-d7dbbd5eacb3", "score": 96, "timestamp": "2026-03-18T11:20:33.216254", "row": 2, "column": 5, "message": "You moved in the specified direction.", "direction": "N", "type": "PlayerMovedEvent"}
{"game_id": "a47fe46f-cfd1-4be3-ad75-d7dbbd5eacb3", "score": 96, "timestamp": "2026-03-18T11:20:34.476904", "row": 1, "column": 5, "character_message": "You found a key!", "points": 1, "type": "CharacterFoundEvent"}
{"game_id": "a47fe46f-cfd1-4be3-ad75-d7dbbd5eacb3", "score": 95, "timestamp": "2026-03-18T11:20:43.914869", "row": 1, "column": 4, "message": "You moved in the specified direction.", "direction": "W", "type": "PlayerMovedEvent"}
{"game_id": "a47fe46f-cfd1-4be3-ad75-d7dbbd5eacb3", "score": 94, "timestamp": "2026-03-18T11:20:45.336877", "row": 1, "column": 3, "message": "You moved in the specified direction.", "direction": "W", "type": "PlayerMovedEvent"}
{"game_id": "a47fe46f-cfd1-4be3-ad75-d7dbbd5eacb3", "score": 93, "timestamp": "2026-03-18T11:20:46.442017", "row": 1, "column": 2, "message": "You moved in the specified direction.", "direction": "W", "type": "PlayerMovedEvent"}
{"game_id": "a47fe46f-cfd1-4be3-ad75-d7dbbd5eacb3", "score": 92, "timestamp": "2026-03-18T11:20:49.901083", "row": 2, "column": 2, "message": "You moved in the specified direction.", "direction": "S", "type": "PlayerMovedEvent"}
{"game_id": "a47fe46f-cfd1-4be3-ad75-d7dbbd5eacb3", "score": 191, "timestamp": "2026-03-18T11:20:50.955923", "row": 3, "column": 2, "message": "You found the exit at specified height and width!", "type": "ExitFoundEvent"}
{"game_id": "e8633414-665b-441a-9307-568f8ae287b6", "score": 100, "timestamp": "2026-03-18T11:24:38.498850", "row": 0, "column": 7, "message": "Game started with specified height and width.", "height": 10, "width": 10, "type": "GameStartedEvent"}
{"game_id": "e8633414-665b-441a-9307-568f8ae287b6", "score": 89, "timestamp": "2026-03-18T11:24:47.999630", "row": 0, "column": 7, "direction": "N", "message": "You are at the end of the board.", "type": "MoveFailedEvent"}
{"game_id": "e8633414-665b-441a-9307-568f8ae287b6", "score": 88, "timestamp": "2026-03-18T11:24:51.036752", "row": 1, "column": 7, "message": "You moved in the specified direction.", "direction": "S", "type": "PlayerMovedEvent"}
{"game_id": "e8633414-665b-441a-9307-568f8ae287b6", "score": 87, "timestamp": "2026-03-18T11:24:51.912168", "row": 2, "column": 7, "message": "You moved in the specified direction.", "direction": "S", "type": "PlayerMovedEvent"}
{"game_id": "e8633414-665b-441a-9307-568f8ae287b6", "score": 86, "timestamp": "2026-03-18T11:24:53.193863", "row": 3, "column": 7, "message": "You moved in the specified direction.", "direction": "S", "type": "PlayerMovedEvent"}
{"game_id": "e8633414-665b-441a-9307-568f8ae287b6", "score": 85, "timestamp": "2026-03-18T11:25:01.663068", "row": 3, "column": 8, "message": "You moved in the specified direction.", "direction": "E", "type": "PlayerMovedEvent"}
{"game_id": "e8633414-665b-441a-9307-568f8ae287b6", "score": 84, "timestamp": "2026-03-18T11:25:02.325677", "row": 3, "column": 9, "message": "You moved in the specified direction.", "direction": "E", "type": "PlayerMovedEvent"}
{"game_id": "e8633414-665b-441a-9307-568f8ae287b6", "score": 73, "timestamp": "2026-03-18T11:25:03.669085", "row": 3, "column": 9, "direction": "E", "message": "You are at the end of the board.", "type": "MoveFailedEvent"}
{"game_id": "e8633414-665b-441a-9307-568f8ae287b6", "score": 72, "timestamp": "2026-03-18T11:25:06.336678", "row": 4, "column": 9, "message": "You moved in the specified direction.", "direction": "S", "type": "PlayerMovedEvent"}
{"game_id": "e8633414-665b-441a-9307-568f8ae287b6", "score": 71, "timestamp": "2026-03-18T11:25:08.144330", "row": 4, "column": 8, "message": "You moved in the specified direction.", "direction": "W", "type": "PlayerMovedEvent"}
{"game_id": "e8633414-665b-441a-9307-568f8ae287b6", "score": 70, "timestamp": "2026-03-18T11:25:08.642181", "row": 4, "column": 7, "message": "You moved in the specified direction.", "direction": "W", "type": "PlayerMovedEvent"}
{"game_id": "e8633414-665b-441a-9307-568f8ae287b6", "score": 69, "timestamp": "2026-03-18T11:25:09.090471", "row": 4, "column": 6, "message": "You moved in the specified direction.", "direction": "W", "type": "PlayerMovedEvent"}
{"game_id": "e8633414-665b-441a-9307-568f8ae287b6", "score": 69, "timestamp": "2026-03-18T11:25:10.213702", "row": 4, "column": 6, "message": "Game ended by user.", "type": "GameEndedEvent"}
{"game_id": "af0c802b-8205-4d9a-a82e-494858cbf32d", "score": 100, "timestamp": "2026-03-18T11:25:14.164898", "row": 6, "column": 1, "message": "Game started with specified height and width.", "height": 10, "width": 10, "type": "GameStartedEvent"}
{"game_id": "af0c802b-8205-4d9a-a82e-494858cbf32d", "score": 99, "timestamp": "2026-03-18T11:25:21.037858", "row": 5, "column": 1, "message": "You moved in the specified direction.", "direction": "N", "type": "PlayerMovedEvent"}
{"game_id": "af0c802b-8205-4d9a-a82e-494858cbf32d", "score": 198, "timestamp": "2026-03-18T11:25:22.781093", "row": 4, "column": 1, "message": "You found the exit at specified height and width!", "type": "ExitFoundEvent"}
{"game_id": "120dd6c9-9cdc-4e7e-9247-e49aa0903e68", "score": 100, "timestamp": "2026-03-18T11:25:28.985568", "row": 9, "column": 1, "message": "Game started with specified height and width.", "height": 10, "width": 10, "type": "GameStartedEvent"}
{"game_id": "120dd6c9-9cdc-4e7e-9247-e49aa0903e68", "score": 99, "timestamp": "2026-03-18T11:25:37.677942", "row": 9, "column": 2, "message": "You moved in the specified direction.", "direction": "E", "type": "PlayerMovedEvent"}
{"game_id": "120dd6c9-9cdc-4e7e-9247-e49aa0903e68", "score": 98, "timestamp": "2026-03-18T11:25:42.267992", "row": 9, "column": 3, "message": "You moved in the specified direction.", "direction": "E", "type": "PlayerMovedEvent"}
{"game_id": "120dd6c9-9cdc-4e7e-9247-e49aa0903e68", "score": 97, "timestamp": "2026-03-18T11:25:44.986368", "row": 8, "column": 3, "message": "You moved in the specified direction.", "direction": "N", "type": "PlayerMovedEvent"}
{"game_id": "120dd6c9-9cdc-4e7e-9247-e49aa0903e68", "score": 96, "timestamp": "2026-03-18T11:26:03.928891", "row": 7, "column": 3, "message": "You moved in the specified direction.", "direction": "N", "type": "PlayerMovedEvent"}
{"game_id": "120dd6c9-9cdc-4e7e-9247-e49aa0903e68", "score": 95, "timestamp": "2026-03-18T11:26:04.979441", "row": 6, "column": 3, "message": "You moved in the specified direction.", "direction": "N", "type": "PlayerMovedEvent"}
{"game_id": "120dd6c9-9cdc-4e7e-9247-e49aa0903e68", "score": 94, "timestamp": "2026-03-18T11:26:06.140093", "row": 5, "column": 3, "message": "You moved in the specified direction.", "direction": "N", "type": "PlayerMovedEvent"}
{"game_id": "120dd6c9-9cdc-4e7e-9247-e49aa0903e68", "score": 93, "timestamp": "2026-03-18T11:26:07.154222", "row": 4, "column": 3, "message": "You moved in the specified direction.", "direction": "N", "type": "PlayerMovedEvent"}
{"game_id": "120dd6c9-9cdc-4e7e-9247-e49aa0903e68", "score": 90, "timestamp": "2026-03-18T11:26:08.329884", "row": 3, "column": 3, "character_message": "You stepped into a puddle of muddy water!", "points": -2, "type": "CharacterFoundEvent"}
{"game_id": "120dd6c9-9cdc-4e7e-9247-e49aa0903e68", "score": 89, "timestamp": "2026-03-18T11:26:18.947865", "row": 2, "column": 3, "message": "You moved in the specified direction.", "direction": "N", "type": "PlayerMovedEvent"}
{"game_id": "120dd6c9-9cdc-4e7e-9247-e49aa0903e68", "score": 88, "timestamp": "2026-03-18T11:26:20.983082", "row": 2, "column": 4, "message": "You moved in the specified direction.", "direction": "E", "type": "PlayerMovedEvent"}
{"game_id": "120dd6c9-9cdc-4e7e-9247-e49aa0903e68", "score": 87, "timestamp": "2026-03-18T11:26:22.565268", "row": 2, "column": 5, "message": "You moved in the specified direction.", "direction": "E", "type": "PlayerMovedEvent"}
{"game_id": "120dd6c9-9cdc-4e7e-9247-e49aa0903e68", "score": 186, "timestamp": "2026-03-18T11:26:24.049217", "row": 2, "column": 6, "message": "You found the exit at specified height and width!", "type": "ExitFoundEvent"}
{"game_id": "40408227-06c3-4fa6-a6c7-818b610146a8", "score": 100, "timestamp": "2026-03-18T11:51:32.440238", "row": 5, "column": 1, "message": "Game started with specified height and width.", "height": 10, "width": 10, "type": "GameStartedEvent"}
{"game_id": "40408227-06c3-4fa6-a6c7-818b610146a8", "score": 99, "timestamp": "2026-03-18T11:51:37.740130", "row": 4, "column": 1, "message": "You moved in the specified direction.", "direction": "N", "type": "PlayerMovedEvent"}
{"game_id": "40408227-06c3-4fa6-a6c7-818b610146a8", "score": 98, "timestamp": "2026-03-18T11:51:39.450511", "row": 4, "column": 2, "message": "You moved in the specified direction.", "direction": "E", "type": "PlayerMovedEvent"}
{"game_id": "40408227-06c3-4fa6-a6c7-818b610146a8", "score": 97, "timestamp": "2026-03-18T11:51:40.216227", "row": 4, "column": 3, "message": "You moved in the specified direction.", "direction": "E", "type": "PlayerMovedEvent"}
{"game_id": "40408227-06c3-4fa6-a6c7-818b610146a8", "score": 96, "timestamp": "2026-03-18T11:51:40.730445", "row": 4, "column": 4, "message": "You moved in the specified direction.", "direction": "E", "type": "PlayerMovedEvent"}
{"game_id": "40408227-06c3-4fa6-a6c7-818b610146a8", "score": 95, "timestamp": "2026-03-18T11:51:41.515203", "row": 3, "column": 4, "message": "You moved in the specified direction.", "direction": "N", "type": "PlayerMovedEvent"}
{"game_id": "40408227-06c3-4fa6-a6c7-818b610146a8", "score": 94, "timestamp": "2026-03-18T11:51:42.154227", "row": 3, "column": 5, "message": "You moved in the specified direction.", "direction": "E", "type": "PlayerMovedEvent"}
{"game_id": "40408227-06c3-4fa6-a6c7-818b610146a8", "score": 93, "timestamp": "2026-03-18T11:51:42.753186", "row": 3, "column": 6, "message": "You moved in the specified direction.", "direction": "E", "type": "PlayerMovedEvent"}
{"game_id": "40408227-06c3-4fa6-a6c7-818b610146a8", "score": 192, "timestamp": "2026-03-18T11:51:43.410520", "row": 3, "column": 7, "message": "You found the exit at specified height and width!", "type": "ExitFoundEvent"}
{"game_id": "e0903690-74e7-4778-a1f5-b97e156eeecc", "score": 100, "timestamp": "2026-03-18T11:51:44.583999", "row": 0, "column": 0, "message": "Game started with specified height and width.", "height": 10, "width": 10, "type": "GameStartedEvent"}
{"game_id": "e0903690-74e7-4778-a1f5-b97e156eeecc", "score": 99, "timestamp": "2026-03-18T11:51:46.246239", "row": 1, "column": 0, "message": "You moved in the specified direction.", "direction": "S", "type": "PlayerMovedEvent"}
{"game_id": "e0903690-74e7-4778-a1f5-b97e156eeecc", "score": 98, "timestamp": "2026-03-18T11:51:46.965700", "row": 2, "column": 0, "message": "You moved in the specified direction.", "direction": "S", "type": "PlayerMovedEvent"}
{"game_id": "e0903690-74e7-4778-a1f5-b97e156eeecc", "score": 97, "timestamp": "2026-03-18T11:51:47.730445", "row": 3, "column": 0, "message": "You moved in the specified direction.", "direction": "S", "type": "PlayerMovedEvent"}
{"game_id": "e0903690-74e7-4778-a1f5-b97e156eeecc", "score": 96, "timestamp": "2026-03-18T11:51:48.225891", "row": 4, "column": 0, "message": "You moved in the specified direction.", "direction": "S", "type": "PlayerMovedEvent"}
{"game_id": "e0903690-74e7-4778-a1f5-b97e156eeecc", "score": 95, "timestamp": "2026-03-18T11:51:48.608999", "row": 5, "column": 0, "message": "You moved in the specified direction.", "direction": "S", "type": "PlayerMovedEvent"}
{"game_id": "e0903690-74e7-4778-a1f5-b97e156eeecc", "score": 94, "timestamp": "2026-03-18T11:51:48.923320", "row": 6, "column": 0, "message": "You moved in the specified direction.", "direction": "S", "type": "PlayerMovedEvent"}
{"game_id": "e0903690-74e7-4778-a1f5-b97e156eeecc", "score": 93, "timestamp": "2026-03-18T11:51:49.237771", "row": 7, "column": 0, "message": "You moved in the specified direction.", "direction": "S", "type": "PlayerMovedEvent"}
{"game_id": "e0903690-74e7-4778-a1f5-b97e156eeecc", "score": 92, "timestamp": "2026-03-18T11:51:50.161080", "row": 8, "column": 0, "message": "You moved in the specified direction.", "direction": "S", "type": "PlayerMovedEvent"}
{"game_id": "e0903690-74e7-4778-a1f5-b97e156eeecc", "score": 91, "timestamp": "2026-03-18T11:51:50.475568", "row": 9, "column": 0, "message": "You moved in the specified direction.", "direction": "S", "type": "PlayerMovedEvent"}
{"game_id": "e0903690-74e7-4778-a1f5-b97e156eeecc", "score": 80, "timestamp": "2026-03-18T11:51:50.770910", "row": 9, "column": 0, "direction": "S", "message": "You are at the end of the board.", "type": "MoveFailedEvent"}
{"game_id": "e0903690-74e7-4778-a1f5-b97e156eeecc", "score": 79, "timestamp": "2026-03-18T11:51:52.950607", "row": 9, "column": 1, "message": "You moved in the specified direction.", "direction": "E", "type": "PlayerMovedEvent"}
{"game_id": "e0903690-74e7-4778-a1f5-b97e156eeecc", "score": 78, "timestamp": "2026-03-18T11:51:53.310851", "row": 9, "column": 2, "message": "You moved in the specified direction.", "direction": "E", "type": "PlayerMovedEvent"}
{"game_id": "e0903690-74e7-4778-a1f5-b97e156eeecc", "score": 77, "timestamp": "2026-03-18T11:51:53.604524", "row": 9, "column": 3, "message": "You moved in the specified direction.", "direction": "E", "type": "PlayerMovedEvent"}
{"game_id": "e0903690-74e7-4778-a1f5-b97e156eeecc", "score": 76, "timestamp": "2026-03-18T11:51:53.873751", "row": 9, "column": 4, "message": "You moved in the specified direction.", "direction": "E", "type": "PlayerMovedEvent"}
{"game_id": "e0903690-74e7-4778-a1f5-b97e156eeecc", "score": 75, "timestamp": "2026-03-18T11:51:54.188333", "row": 9, "column": 5, "message": "You moved in the specified direction.", "direction": "E", "type": "PlayerMovedEvent"}
{"game_id": "e0903690-74e7-4778-a1f5-b97e156eeecc", "score": 74, "timestamp": "2026-03-18T11:51:54.970272", "row": 9, "column": 6, "message": "You moved in the specified direction.", "direction": "E", "type": "PlayerMovedEvent"}
{"game_id": "e0903690-74e7-4778-a1f5-b97e156eeecc", "score": 73, "timestamp": "2026-03-18T11:51:55.425160", "row": 9, "column": 7, "message": "You moved in the specified direction.", "direction": "E", "type": "PlayerMovedEvent"}
{"game_id": "e0903690-74e7-4778-a1f5-b97e156eeecc", "score": 72, "timestamp": "2026-03-18T11:51:55.830094", "row": 9, "column": 8, "message": "You moved in the specified direction.", "direction": "E", "type": "PlayerMovedEvent"}
{"game_id": "e0903690-74e7-4778-a1f5-b97e156eeecc", "score": 71, "timestamp": "2026-03-18T11:51:56.258646", "row": 9, "column": 9, "message": "You moved in the specified direction.", "direction": "E", "type": "PlayerMovedEvent"}
{"game_id": "e0903690-74e7-4778-a1f5-b97e156eeecc", "score": 60, "timestamp": "2026-03-18T11:51:56.664360", "row": 9, "column": 9, "direction": "E", "message": "You are at the end of the board.", "type": "MoveFailedEvent"}
{"game_id": "e0903690-74e7-4778-a1f5-b97e156eeecc", "score": 59, "timestamp": "2026-03-18T11:51:58.531093", "row": 8, "column": 9, "message": "You moved in the specified direction.", "direction": "N", "type": "PlayerMovedEvent"}
{"game_id": "e0903690-74e7-4778-a1f5-b97e156eeecc", "score": 58, "timestamp": "2026-03-18T11:51:58.867877", "row": 7, "column": 9, "message": "You moved in the specified direction.", "direction": "N", "type": "PlayerMovedEvent"}
{"game_id": "e0903690-74e7-4778-a1f5-b97e156eeecc", "score": 57, "timestamp": "2026-03-18T11:52:01.523056", "row": 6, "column": 9, "message": "You moved in the specified direction.", "direction": "N", "type": "PlayerMovedEvent"}
{"game_id": "e0903690-74e7-4778-a1f5-b97e156eeecc", "score": 56, "timestamp": "2026-03-18T11:52:02.513335", "row": 6, "column": 8, "message": "You moved in the specified direction.", "direction": "W", "type": "PlayerMovedEvent"}
{"game_id": "e0903690-74e7-4778-a1f5-b97e156eeecc", "score": 55, "timestamp": "2026-03-18T11:52:03.075387", "row": 5, "column": 8, "message": "You moved in the specified direction.", "direction": "N", "type": "PlayerMovedEvent"}
{"game_id": "e0903690-74e7-4778-a1f5-b97e156eeecc", "score": 54, "timestamp": "2026-03-18T11:52:03.524834", "row": 5, "column": 7, "message": "You moved in the specified direction.", "direction": "W", "type": "PlayerMovedEvent"}
{"game_id": "e0903690-74e7-4778-a1f5-b97e156eeecc", "score": 53, "timestamp": "2026-03-18T11:52:03.998097", "row": 4, "column": 7, "message": "You moved in the specified direction.", "direction": "N", "type": "PlayerMovedEvent"}
{"game_id": "e0903690-74e7-4778-a1f5-b97e156eeecc", "score": 52, "timestamp": "2026-03-18T11:52:04.425498", "row": 4, "column": 6, "message": "You moved in the specified direction.", "direction": "W", "type": "PlayerMovedEvent"}
{"game_id": "e0903690-74e7-4778-a1f5-b97e156eeecc", "score": 51, "timestamp": "2026-03-18T11:52:05.011245", "row": 3, "column": 6, "message": "You moved in the specified direction.", "direction": "N", "type": "PlayerMovedEvent"}
{"game_id": "e0903690-74e7-4778-a1f5-b97e156eeecc", "score": 50, "timestamp": "2026-03-18T11:52:05.502136", "row": 3, "column": 5, "message": "You moved in the specified direction.", "direction": "W", "type": "PlayerMovedEvent"}
{"game_id": "e0903690-74e7-4778-a1f5-b97e156eeecc", "score": 49, "timestamp": "2026-03-18T11:52:05.955601", "row": 2, "column": 5, "message": "You moved in the specified direction.", "direction": "N", "type": "PlayerMovedEvent"}
{"game_id": "e0903690-74e7-4778-a1f5-b97e156eeecc", "score": 148, "timestamp": "2026-03-18T11:52:06.629800", "row": 2, "column": 4, "message": "You found the exit at specified height and width!", "type": "ExitFoundEvent"}
{"game_id": "5b3fc97b-73d8-441c-9d69-1108b8bc57b7", "score": 100, "timestamp": "2026-03-18T11:52:07.807990", "row": 7, "column": 8, "message": "Game started with specified height and width.", "height": 10, "width": 10, "type": "GameStartedEvent"}
{"game_id": "5b3fc97b-73d8-441c-9d69-1108b8bc57b7", "score": 99, "timestamp": "2026-03-18T11:53:43.498589", "row": 7, "column": 9, "message": "You moved in the specified direction.", "direction": "E", "type": "PlayerMovedEvent"}
{"game_id": "5b3fc97b-73d8-441c-9d69-1108b8bc57b7", "score": 98, "timestamp": "2026-03-18T11:53:45.002500", "row": 7, "column": 8, "message": "You moved in the specified direction.", "direction": "W", "type": "PlayerMovedEvent"}
{"game_id": "5b3fc97b-73d8-441c-9d69-1108b8bc57b7", "score": 97, "timestamp": "2026-03-18T11:53:46.237954", "row": 8, "column": 8, "message": "You moved in the specified direction.", "direction": "S", "type": "PlayerMovedEvent"}
{"game_id": "5b3fc97b-73d8-441c-9d69-1108b8bc57b7", "score": 95, "timestamp": "2026-03-18T11:53:47.048385", "row": 9, "column": 8, "character_message": "You hit a wall!", "points": -1, "type": "CharacterFoundEvent"}
{"game_id": "5b3fc97b-73d8-441c-9d69-1108b8bc57b7", "score": 94, "timestamp": "2026-03-18T11:53:48.286093", "row": 9, "column": 7, "message": "You moved in the specified direction.", "direction": "W", "type": "PlayerMovedEvent"}
{"game_id": "5b3fc97b-73d8-441c-9d69-1108b8bc57b7", "score": 83, "timestamp": "2026-03-18T11:53:49.249626", "row": 9, "column": 7, "direction": "S", "message": "You are at the end of the board.", "type": "MoveFailedEvent"}
{"game_id": "5b3fc97b-73d8-441c-9d69-1108b8bc57b7", "score": 82, "timestamp": "2026-03-18T11:53:50.019500", "row": 9, "column": 6, "message": "You moved in the specified direction.", "direction": "W", "type": "PlayerMovedEvent"}
{"game_id": "5b3fc97b-73d8-441c-9d69-1108b8bc57b7", "score": 81, "timestamp": "2026-03-18T11:53:51.116326", "row": 9, "column": 5, "message": "You moved in the specified direction.", "direction": "W", "type": "PlayerMovedEvent"}
{"game_id": "5b3fc97b-73d8-441c-9d69-1108b8bc57b7", "score": 80, "timestamp": "2026-03-18T11:53:52.066221", "row": 9, "column": 4, "message": "You moved in the specified direction.", "direction": "W", "type": "PlayerMovedEvent"}
{"game_id": "5b3fc97b-73d8-441c-9d69-1108b8bc57b7", "score": 179, "timestamp": "2026-03-18T11:53:52.718050", "row": 9, "column": 3, "message": "You found the exit at specified height and width!", "type": "ExitFoundEvent"}
{"game_id": "cff27f20-0def-4634-b895-868f5b4a47b7", "score": 100, "timestamp": "2026-03-18T11:53:54.161819", "row": 8, "column": 6, "message": "Game started with specified height and width.", "height": 10, "width": 10, "type": "GameStartedEvent"}
{"game_id": "cff27f20-0def-4634-b895-868f5b4a47b7", "score": 99, "timestamp": "2026-03-18T11:53:55.913295", "row": 8, "column": 7, "message": "You moved in the specified direction.", "direction": "E", "type": "PlayerMovedEvent"}
{"game_id": "cff27f20-0def-4634-b895-868f5b4a47b7", "score": 98, "timestamp": "2026-03-18T11:53:57.465968", "row": 8, "column": 6, "message": "You moved in the specified direction.", "direction": "W", "type": "PlayerMovedEvent"}
{"game_id": "cff27f20-0def-4634-b895-868f5b4a47b7", "score": 97, "timestamp": "2026-03-18T11:53:58.073297", "row": 8, "column": 5, "message": "You moved in the specified direction.", "direction": "W", "type": "PlayerMovedEvent"}
{"game_id": "cff27f20-0def-4634-b895-868f5b4a47b7", "score": 96, "timestamp": "2026-03-18T11:53:58.635701", "row": 8, "column": 4, "message": "You moved in the specified direction.", "direction": "W", "type": "PlayerMovedEvent"}
{"game_id": "cff27f20-0def-4634-b895-868f5b4a47b7", "score": 95, "timestamp": "2026-03-18T11:53:59.107867", "row": 8, "column": 3, "message": "You moved in the specified direction.", "direction": "W", "type": "PlayerMovedEvent"}
{"game_id": "cff27f20-0def-4634-b895-868f5b4a47b7", "score": 94, "timestamp": "2026-03-18T11:53:59.534348", "row": 8, "column": 2, "message": "You moved in the specified direction.", "direction": "W", "type": "PlayerMovedEvent"}
{"game_id": "cff27f20-0def-4634-b895-868f5b4a47b7", "score": 193, "timestamp": "2026-03-18T11:54:00.030925", "row": 8, "column": 1, "message": "You found the exit at specified height and width!", "type": "ExitFoundEvent"}
{"game_id": "a4627aa3-6d3c-4745-8952-e2a47a85f4e4", "score": 100, "timestamp": "2026-03-18T11:54:00.912772", "row": 2, "column": 9, "message": "Game started with specified height and width.", "height": 10, "width": 10, "type": "GameStartedEvent"}
{"game_id": "a4627aa3-6d3c-4745-8952-e2a47a85f4e4", "score": 99, "timestamp": "2026-03-18T11:54:01.806455", "row": 3, "column": 9, "message": "You moved in the specified direction.", "direction": "S", "type": "PlayerMovedEvent"}
{"game_id": "a4627aa3-6d3c-4745-8952-e2a47a85f4e4", "score": 103, "timestamp": "2026-03-18T11:54:03.181188", "row": 3, "column": 8, "character_message": "You found a gem", "points": 5, "type": "CharacterFoundEvent"}
{"game_id": "a4627aa3-6d3c-4745-8952-e2a47a85f4e4", "score": 102, "timestamp": "2026-03-18T11:54:03.630459", "row": 3, "column": 9, "message": "You moved in the specified direction.", "direction": "E", "type": "PlayerMovedEvent"}
{"game_id": "a4627aa3-6d3c-4745-8952-e2a47a85f4e4", "score": 101, "timestamp": "2026-03-18T11:54:03.900818", "row": 4, "column": 9, "message": "You moved in the specified direction.", "direction": "S", "type": "PlayerMovedEvent"}
{"game_id": "a4627aa3-6d3c-4745-8952-e2a47a85f4e4", "score": 100, "timestamp": "2026-03-18T11:54:04.505875", "row": 5, "column": 9, "message": "You moved in the specified direction.", "direction": "S", "type": "PlayerMovedEvent"}
{"game_id": "a4627aa3-6d3c-4745-8952-e2a47a85f4e4", "score": 99, "timestamp": "2026-03-18T11:54:04.867770", "row": 6, "column": 9, "message": "You moved in the specified direction.", "direction": "S", "type": "PlayerMovedEvent"}
{"game_id": "a4627aa3-6d3c-4745-8952-e2a47a85f4e4", "score": 98, "timestamp": "2026-03-18T11:54:05.317869", "row": 6, "column": 8, "message": "You moved in the specified direction.", "direction": "W", "type": "PlayerMovedEvent"}
{"game_id": "a4627aa3-6d3c-4745-8952-e2a47a85f4e4", "score": 97, "timestamp": "2026-03-18T11:54:06.016305", "row": 6, "column": 9, "message": "You moved in the specified direction.", "direction": "E", "type": "PlayerMovedEvent"}
{"game_id": "a4627aa3-6d3c-4745-8952-e2a47a85f4e4", "score": 96, "timestamp": "2026-03-18T11:54:06.803115", "row": 6, "column": 8, "message": "You moved in the specified direction.", "direction": "W", "type": "PlayerMovedEvent"}
{"game_id": "a4627aa3-6d3c-4745-8952-e2a47a85f4e4", "score": 95, "timestamp": "2026-03-18T11:54:07.207843", "row": 6, "column": 7, "message": "You moved in the specified direction.", "direction": "W", "type": "PlayerMovedEvent"}
{"game_id": "a4627aa3-6d3c-4745-8952-e2a47a85f4e4", "score": 94, "timestamp": "2026-03-18T11:54:07.612996", "row": 7, "column": 7, "message": "You moved in the specified direction.", "direction": "S", "type": "PlayerMovedEvent"}
{"game_id": "a4627aa3-6d3c-4745-8952-e2a47a85f4e4", "score": 93, "timestamp": "2026-03-18T11:54:07.882946", "row": 7, "column": 6, "message": "You moved in the specified direction.", "direction": "W", "type": "PlayerMovedEvent"}
{"game_id": "a4627aa3-6d3c-4745-8952-e2a47a85f4e4", "score": 92, "timestamp": "2026-03-18T11:54:08.199009", "row": 8, "column": 6, "message": "You moved in the specified direction.", "direction": "S", "type": "PlayerMovedEvent"}
{"game_id": "a4627aa3-6d3c-4745-8952-e2a47a85f4e4", "score": 191, "timestamp": "2026-03-18T11:54:08.513363", "row": 8, "column": 5, "message": "You found the exit at specified height and width!", "type": "ExitFoundEvent"}
{"game_id": "c8363ed7-a750-4783-a3a2-63e8e3fea2e2", "score": 100, "timestamp": "2026-03-18T11:54:09.559591", "row": 6, "column": 7, "message": "Game started with specified height and width.", "height": 10, "width": 10, "type": "GameStartedEvent"}
{"game_id": "c8363ed7-a750-4783-a3a2-63e8e3fea2e2", "score": 99, "timestamp": "2026-03-18T11:54:16.337876", "row": 7, "column": 7, "message": "You moved in the specified direction.", "direction": "S", "type": "PlayerMovedEvent"}
{"game_id": "c8363ed7-a750-4783-a3a2-63e8e3fea2e2", "score": 98, "timestamp": "2026-03-18T11:54:17.490964", "row": 6, "column": 7, "message": "You moved in the specified direction.", "direction": "N", "type": "PlayerMovedEvent"}
{"game_id": "c8363ed7-a750-4783-a3a2-63e8e3fea2e2", "score": 97, "timestamp": "2026-03-18T11:54:18.773479", "row": 6, "column": 6, "message": "You moved in the specified direction.", "direction": "W", "type": "PlayerMovedEvent"}
{"game_id": "c8363ed7-a750-4783-a3a2-63e8e3fea2e2", "score": 96, "timestamp": "2026-03-18T11:54:19.605867", "row": 6, "column": 5, "message": "You moved in the specified direction.", "direction": "W", "type": "PlayerMovedEvent"}
{"game_id": "c8363ed7-a750-4783-a3a2-63e8e3fea2e2", "score": 95, "timestamp": "2026-03-18T11:54:20.212835", "row": 6, "column": 6, "message": "You moved in the specified direction.", "direction": "E", "type": "PlayerMovedEvent"}
{"game_id": "c8363ed7-a750-4783-a3a2-63e8e3fea2e2", "score": 94, "timestamp": "2026-03-18T11:54:20.663214", "row": 6, "column": 7, "message": "You moved in the specified direction.", "direction": "E", "type": "PlayerMovedEvent"}
{"game_id": "c8363ed7-a750-4783-a3a2-63e8e3fea2e2", "score": 93, "timestamp": "2026-03-18T11:54:21.338120", "row": 5, "column": 7, "message": "You moved in the specified direction.", "direction": "N", "type": "PlayerMovedEvent"}
{"game_id": "c8363ed7-a750-4783-a3a2-63e8e3fea2e2", "score": 92, "timestamp": "2026-03-18T11:54:21.742628", "row": 4, "column": 7, "message": "You moved in the specified direction.", "direction": "N", "type": "PlayerMovedEvent"}
{"game_id": "c8363ed7-a750-4783-a3a2-63e8e3fea2e2", "score": 91, "timestamp": "2026-03-18T11:54:22.171917", "row": 4, "column": 8, "message": "You moved in the specified direction.", "direction": "E", "type": "PlayerMovedEvent"}
{"game_id": "c8363ed7-a750-4783-a3a2-63e8e3fea2e2", "score": 90, "timestamp": "2026-03-18T11:54:22.553629", "row": 4, "column": 7, "message": "You moved in the specified direction.", "direction": "W", "type": "PlayerMovedEvent"}
{"game_id": "c8363ed7-a750-4783-a3a2-63e8e3fea2e2", "score": 87, "timestamp": "2026-03-18T11:54:23.112606", "row": 3, "column": 7, "character_message": "You stepped into a puddle of muddy water!", "points": -2, "type": "CharacterFoundEvent"}
{"game_id": "c8363ed7-a750-4783-a3a2-63e8e3fea2e2", "score": 86, "timestamp": "2026-03-18T11:54:25.051847", "row": 2, "column": 7, "message": "You moved in the specified direction.", "direction": "N", "type": "PlayerMovedEvent"}
{"game_id": "c8363ed7-a750-4783-a3a2-63e8e3fea2e2", "score": 85, "timestamp": "2026-03-18T11:54:25.951000", "row": 1, "column": 7, "message": "You moved in the specified direction.", "direction": "N", "type": "PlayerMovedEvent"}
{"game_id": "c8363ed7-a750-4783-a3a2-63e8e3fea2e2", "score": 184, "timestamp": "2026-03-18T11:54:26.604875", "row": 0, "column": 7, "message": "You found the exit at specified height and width!", "type": "ExitFoundEvent"}
{"game_id": "e8a228d4-01fc-462f-b11a-61fd9d290535", "score": 100, "timestamp": "2026-03-18T11:54:27.440299", "row": 9, "column": 8, "message": "Game started with specified height and width.", "height": 10, "width": 10, "type": "GameStartedEvent"}
{"game_id": "e8a228d4-01fc-462f-b11a-61fd9d290535", "score": 99, "timestamp": "2026-03-18T11:54:28.426303", "row": 8, "column": 8, "message": "You moved in the specified direction.", "direction": "N", "type": "PlayerMovedEvent"}
{"game_id": "e8a228d4-01fc-462f-b11a-61fd9d290535", "score": 98, "timestamp": "2026-03-18T11:54:29.642014", "row": 8, "column": 7, "message": "You moved in the specified direction.", "direction": "W", "type": "PlayerMovedEvent"}
{"game_id": "e8a228d4-01fc-462f-b11a-61fd9d290535", "score": 97, "timestamp": "2026-03-18T11:54:30.202724", "row": 7, "column": 7, "message": "You moved in the specified direction.", "direction": "N", "type": "PlayerMovedEvent"}
{"game_id": "e8a228d4-01fc-462f-b11a-61fd9d290535", "score": 96, "timestamp": "2026-03-18T11:54:30.720643", "row": 7, "column": 6, "message": "You moved in the specified direction.", "direction": "W", "type": "PlayerMovedEvent"}
{"game_id": "e8a228d4-01fc-462f-b11a-61fd9d290535", "score": 95, "timestamp": "2026-03-18T11:54:31.211126", "row": 7, "column": 5, "message": "You moved in the specified direction.", "direction": "W", "type": "PlayerMovedEvent"}
{"game_id": "e8a228d4-01fc-462f-b11a-61fd9d290535", "score": 95, "timestamp": "2026-03-18T11:54:31.598841", "row": 7, "column": 4, "character_message": "You found a key!", "points": 1, "type": "CharacterFoundEvent"}
{"game_id": "e8a228d4-01fc-462f-b11a-61fd9d290535", "score": 94, "timestamp": "2026-03-18T11:54:32.743233", "row": 7, "column": 3, "message": "You moved in the specified direction.", "direction": "W", "type": "PlayerMovedEvent"}
{"game_id": "e8a228d4-01fc-462f-b11a-61fd9d290535", "score": 93, "timestamp": "2026-03-18T11:54:33.376253", "row": 7, "column": 2, "message": "You moved in the specified direction.", "direction": "W", "type": "PlayerMovedEvent"}
{"game_id": "e8a228d4-01fc-462f-b11a-61fd9d290535", "score": 92, "timestamp": "2026-03-18T11:54:33.893765", "row": 7, "column": 1, "message": "You moved in the specified direction.", "direction": "W", "type": "PlayerMovedEvent"}
{"game_id": "e8a228d4-01fc-462f-b11a-61fd9d290535", "score": 191, "timestamp": "2026-03-18T11:54:34.320544", "row": 7, "column": 0, "message": "You found the exit at specified height and width!", "type": "ExitFoundEvent"}
{"game_id": "f3553faa-c47e-4fcd-86d7-d62706533e4c", "score": 100, "timestamp": "2026-03-18T11:54:35.270192", "row": 5, "column": 6, "message": "Game started with specified height and width.", "height": 10, "width": 10, "type": "GameStartedEvent"}
{"game_id": "f3553faa-c47e-4fcd-86d7-d62706533e4c", "score": 99, "timestamp": "2026-03-18T11:54:36.052583", "row": 5, "column": 5, "message": "You moved in the specified direction.", "direction": "W", "type": "PlayerMovedEvent"}
{"game_id": "f3553faa-c47e-4fcd-86d7-d62706533e4c", "score": 98, "timestamp": "2026-03-18T11:54:37.088235", "row": 5, "column": 6, "message": "You moved in the specified direction.", "direction": "E", "type": "PlayerMovedEvent"}
{"game_id": "f3553faa-c47e-4fcd-86d7-d62706533e4c", "score": 97, "timestamp": "2026-03-18T11:54:38.145757", "row": 4, "column": 6, "message": "You moved in the specified direction.", "direction": "N", "type": "PlayerMovedEvent"}
{"game_id": "f3553faa-c47e-4fcd-86d7-d62706533e4c", "score": 96, "timestamp": "2026-03-18T11:54:38.865702", "row": 4, "column": 7, "message": "You moved in the specified direction.", "direction": "E", "type": "PlayerMovedEvent"}
{"game_id": "f3553faa-c47e-4fcd-86d7-d62706533e4c", "score": 96, "timestamp": "2026-03-18T11:54:39.315972", "row": 3, "column": 7, "character_message": "You found a key!", "points": 1, "type": "CharacterFoundEvent"}
{"game_id": "f3553faa-c47e-4fcd-86d7-d62706533e4c", "score": 195, "timestamp": "2026-03-18T11:54:40.012920", "row": 3, "column": 8, "message": "You found the exit at specified height and width!", "type": "ExitFoundEvent"}
{"game_id": "aef1d50b-c5e4-42c7-9945-9ae5a79f1ad3", "score": 100, "timestamp": "2026-03-18T11:54:41.314906", "row": 3, "column": 7, "message": "Game started with specified height and width.", "height": 10, "width": 10, "type": "GameStartedEvent"}
{"game_id": "aef1d50b-c5e4-42c7-9945-9ae5a79f1ad3", "score": 99, "timestamp": "2026-03-18T11:54:43.630906", "row": 2, "column": 7, "message": "You moved in the specified direction.", "direction": "N", "type": "PlayerMovedEvent"}
{"game_id": "aef1d50b-c5e4-42c7-9945-9ae5a79f1ad3", "score": 98, "timestamp": "2026-03-18T11:54:45.234289", "row": 3, "column": 7, "message": "You moved in the specified direction.", "direction": "S", "type": "PlayerMovedEvent"}
{"game_id": "aef1d50b-c5e4-42c7-9945-9ae5a79f1ad3", "score": 97, "timestamp": "2026-03-18T11:54:45.952391", "row": 3, "column": 6, "message": "You moved in the specified direction.", "direction": "W", "type": "PlayerMovedEvent"}
{"game_id": "aef1d50b-c5e4-42c7-9945-9ae5a79f1ad3", "score": 96, "timestamp": "2026-03-18T11:54:46.605983", "row": 4, "column": 6, "message": "You moved in the specified direction.", "direction": "S", "type": "PlayerMovedEvent"}
{"game_id": "aef1d50b-c5e4-42c7-9945-9ae5a79f1ad3", "score": 100, "timestamp": "2026-03-18T11:54:47.079024", "row": 4, "column": 5, "character_message": "You found a gem", "points": 5, "type": "CharacterFoundEvent"}
{"game_id": "aef1d50b-c5e4-42c7-9945-9ae5a79f1ad3", "score": 99, "timestamp": "2026-03-18T11:54:47.664054", "row": 5, "column": 5, "message": "You moved in the specified direction.", "direction": "S", "type": "PlayerMovedEvent"}
{"game_id": "aef1d50b-c5e4-42c7-9945-9ae5a79f1ad3", "score": 98, "timestamp": "2026-03-18T11:54:48.405868", "row": 5, "column": 4, "message": "You moved in the specified direction.", "direction": "W", "type": "PlayerMovedEvent"}
{"game_id": "aef1d50b-c5e4-42c7-9945-9ae5a79f1ad3", "score": 97, "timestamp": "2026-03-18T11:54:48.855168", "row": 6, "column": 4, "message": "You moved in the specified direction.", "direction": "S", "type": "PlayerMovedEvent"}
{"game_id": "aef1d50b-c5e4-42c7-9945-9ae5a79f1ad3", "score": 196, "timestamp": "2026-03-18T11:54:49.328754", "row": 6, "column": 3, "message": "You found the exit at specified height and width!", "type": "ExitFoundEvent"}
{"game_id": "fb15e45a-4ff4-4160-9c98-f85c35eee24a", "score": 100, "timestamp": "2026-03-18T11:55:36.572298", "row": 9, "column": 1, "message": "Game started with specified height and width.", "height": 10, "width": 10, "type": "GameStartedEvent"}
{"game_id": "fb15e45a-4ff4-4160-9c98-f85c35eee24a", "score": 99, "timestamp": "2026-03-18T11:55:39.365935", "row": 9, "column": 2, "message": "You moved in the specified direction.", "direction": "E", "type": "PlayerMovedEvent"}
{"game_id": "fb15e45a-4ff4-4160-9c98-f85c35eee24a", "score": 98, "timestamp": "2026-03-18T11:55:41.100931", "row": 8, "column": 2, "message": "You moved in the specified direction.", "direction": "N", "type": "PlayerMovedEvent"}
{"game_id": "fb15e45a-4ff4-4160-9c98-f85c35eee24a", "score": 97, "timestamp": "2026-03-18T11:55:41.618900", "row": 8, "column": 3, "message": "You moved in the specified direction.", "direction": "E", "type": "PlayerMovedEvent"}
{"game_id": "fb15e45a-4ff4-4160-9c98-f85c35eee24a", "score": 96, "timestamp": "2026-03-18T11:55:42.855866", "row": 7, "column": 3, "message": "You moved in the specified direction.", "direction": "N", "type": "PlayerMovedEvent"}
{"game_id": "fb15e45a-4ff4-4160-9c98-f85c35eee24a", "score": 95, "timestamp": "2026-03-18T11:55:43.328944", "row": 6, "column": 3, "message": "You moved in the specified direction.", "direction": "N", "type": "PlayerMovedEvent"}
{"game_id": "fb15e45a-4ff4-4160-9c98-f85c35eee24a", "score": 94, "timestamp": "2026-03-18T11:55:43.689904", "row": 5, "column": 3, "message": "You moved in the specified direction.", "direction": "N", "type": "PlayerMovedEvent"}
{"game_id": "fb15e45a-4ff4-4160-9c98-f85c35eee24a", "score": 93, "timestamp": "2026-03-18T11:55:44.071189", "row": 4, "column": 3, "message": "You moved in the specified direction.", "direction": "N", "type": "PlayerMovedEvent"}
{"game_id": "fb15e45a-4ff4-4160-9c98-f85c35eee24a", "score": 92, "timestamp": "2026-03-18T11:55:44.427969", "row": 3, "column": 3, "message": "You moved in the specified direction.", "direction": "N", "type": "PlayerMovedEvent"}
{"game_id": "fb15e45a-4ff4-4160-9c98-f85c35eee24a", "score": 91, "timestamp": "2026-03-18T11:55:44.837466", "row": 2, "column": 3, "message": "You moved in the specified direction.", "direction": "N", "type": "PlayerMovedEvent"}
{"game_id": "fb15e45a-4ff4-4160-9c98-f85c35eee24a", "score": 190, "timestamp": "2026-03-18T11:55:45.174450", "row": 1, "column": 3, "message": "You found the exit at specified height and width!", "type": "ExitFoundEvent"}
{"game_id": "6b16c72f-bbe0-46ab-ab34-f2c9e3a3fec3", "score": 100, "timestamp": "2026-03-18T13:34:54.888738", "row": 4, "column": 8, "message": "Game started with specified height and width.", "height": 10, "width": 10, "type": "GameStartedEvent"}
{"game_id": "6b16c72f-bbe0-46ab-ab34-f2c9e3a3fec3", "score": 99, "timestamp": "2026-03-18T13:34:56.871902", "row": 3, "column": 8, "message": "You moved in the specified direction.", "direction": "N", "type": "PlayerMovedEvent"}
{"game_id": "6b16c72f-bbe0-46ab-ab34-f2c9e3a3fec3", "score": 98, "timestamp": "2026-03-18T13:34:58.580612", "row": 2, "column": 8, "message": "You moved in the specified direction.", "direction": "N", "type": "PlayerMovedEvent"}
{"game_id": "6b16c72f-bbe0-46ab-ab34-f2c9e3a3fec3", "score": 197, "timestamp": "2026-03-18T13:34:59.053870", "row": 1, "column": 8, "message": "You found the exit at specified height and width!", "type": "ExitFoundEvent"}
{"game_id": "6b9c89b3-dd55-4005-8f52-3ad59eab433c", "score": 100, "timestamp": "2026-03-18T13:35:00.051885", "row": 1, "column": 3, "message": "Game started with specified height and width.", "height": 10, "width": 10, "type": "GameStartedEvent"}
{"game_id": "6b9c89b3-dd55-4005-8f52-3ad59eab433c", "score": 99, "timestamp": "2026-03-18T13:35:01.237819", "row": 1, "column": 4, "message": "You moved in the specified direction.", "direction": "E", "type": "PlayerMovedEvent"}
{"game_id": "6b9c89b3-dd55-4005-8f52-3ad59eab433c", "score": 98, "timestamp": "2026-03-18T13:35:01.711382", "row": 2, "column": 4, "message": "You moved in the specified direction.", "direction": "S", "type": "PlayerMovedEvent"}
{"game_id": "6b9c89b3-dd55-4005-8f52-3ad59eab433c", "score": 97, "timestamp": "2026-03-18T13:35:02.047770", "row": 2, "column": 3, "message": "You moved in the specified direction.", "direction": "W", "type": "PlayerMovedEvent"}
{"game_id": "6b9c89b3-dd55-4005-8f52-3ad59eab433c", "score": 96, "timestamp": "2026-03-18T13:35:02.880547", "row": 2, "column": 4, "message": "You moved in the specified direction.", "direction": "E", "type": "PlayerMovedEvent"}
{"game_id": "6b9c89b3-dd55-4005-8f52-3ad59eab433c", "score": 95, "timestamp": "2026-03-18T13:35:03.938771", "row": 2, "column": 5, "message": "You moved in the specified direction.", "direction": "E", "type": "PlayerMovedEvent"}
{"game_id": "6b9c89b3-dd55-4005-8f52-3ad59eab433c", "score": 94, "timestamp": "2026-03-18T13:35:04.339061", "row": 2, "column": 4, "message": "You moved in the specified direction.", "direction": "W", "type": "PlayerMovedEvent"}
{"game_id": "6b9c89b3-dd55-4005-8f52-3ad59eab433c", "score": 93, "timestamp": "2026-03-18T13:35:05.760899", "row": 3, "column": 4, "message": "You moved in the specified direction.", "direction": "S", "type": "PlayerMovedEvent"}
{"game_id": "6b9c89b3-dd55-4005-8f52-3ad59eab433c", "score": 92, "timestamp": "2026-03-18T13:35:06.251475", "row": 3, "column": 5, "message": "You moved in the specified direction.", "direction": "E", "type": "PlayerMovedEvent"}
{"game_id": "6b9c89b3-dd55-4005-8f52-3ad59eab433c", "score": 91, "timestamp": "2026-03-18T13:35:06.705824", "row": 4, "column": 5, "message": "You moved in the specified direction.", "direction": "S", "type": "PlayerMovedEvent"}
{"game_id": "6b9c89b3-dd55-4005-8f52-3ad59eab433c", "score": 90, "timestamp": "2026-03-18T13:35:07.090157", "row": 4, "column": 6, "message": "You moved in the specified direction.", "direction": "E", "type": "PlayerMovedEvent"}
{"game_id": "6b9c89b3-dd55-4005-8f52-3ad59eab433c", "score": 88, "timestamp": "2026-03-18T13:35:07.785612", "row": 5, "column": 6, "character_message": "You hit a monster!", "points": -1, "type": "CharacterFoundEvent"}
{"game_id": "6b9c89b3-dd55-4005-8f52-3ad59eab433c", "score": 87, "timestamp": "2026-03-18T13:35:09.495809", "row": 6, "column": 6, "message": "You moved in the specified direction.", "direction": "S", "type": "PlayerMovedEvent"}
{"game_id": "6b9c89b3-dd55-4005-8f52-3ad59eab433c", "score": 186, "timestamp": "2026-03-18T13:35:10.172229", "row": 7, "column": 6, "message": "You found the exit at specified height and width!", "type": "ExitFoundEvent"}
{"game_id": "32afb5b1-b566-457c-aebb-658617f5d270", "score": 100, "timestamp": "2026-03-18T13:35:11.032387", "row": 3, "column": 7, "message": "Game started with specified height and width.", "height": 10, "width": 10, "type": "GameStartedEvent"}
{"game_id": "32afb5b1-b566-457c-aebb-658617f5d270", "score": 99, "timestamp": "2026-03-18T13:35:12.377126", "row": 2, "column": 7, "message": "You moved in the specified direction.", "direction": "N", "type": "PlayerMovedEvent"}
{"game_id": "32afb5b1-b566-457c-aebb-658617f5d270", "score": 98, "timestamp": "2026-03-18T13:35:13.387746", "row": 3, "column": 7, "message": "You moved in the specified direction.", "direction": "S", "type": "PlayerMovedEvent"}
{"game_id": "32afb5b1-b566-457c-aebb-658617f5d270", "score": 97, "timestamp": "2026-03-18T13:35:13.837601", "row": 3, "column": 6, "message": "You moved in the specified direction.", "direction": "W", "type": "PlayerMovedEvent"}
{"game_id": "32afb5b1-b566-457c-aebb-658617f5d270", "score": 96, "timestamp": "2026-03-18T13:35:14.423893", "row": 4, "column": 6, "message": "You moved in the specified direction.", "direction": "S", "type": "PlayerMovedEvent"}
{"game_id": "32afb5b1-b566-457c-aebb-658617f5d270", "score": 95, "timestamp": "2026-03-18T13:35:14.891065", "row": 5, "column": 6, "message": "You moved in the specified direction.", "direction": "S", "type": "PlayerMovedEvent"}
{"game_id": "32afb5b1-b566-457c-aebb-658617f5d270", "score": 94, "timestamp": "2026-03-18T13:35:15.255100", "row": 6, "column": 6, "message": "You moved in the specified direction.", "direction": "S", "type": "PlayerMovedEvent"}
{"game_id": "32afb5b1-b566-457c-aebb-658617f5d270", "score": 193, "timestamp": "2026-03-18T13:35:15.683259", "row": 7, "column": 6, "message": "You found the exit at specified height and width!", "type": "ExitFoundEvent"}
{"game_id": "459eb519-4b5c-4cc8-88ef-86865c10d287", "score": 100, "timestamp": "2026-03-18T13:35:16.566774", "row": 9, "column": 0, "message": "Game started with specified height and width.", "height": 10, "width": 10, "type": "GameStartedEvent"}
{"game_id": "459eb519-4b5c-4cc8-88ef-86865c10d287", "score": 199, "timestamp": "2026-03-18T13:35:18.469233", "row": 8, "column": 0, "message": "You found the exit at specified height and width!", "type": "ExitFoundEvent"}
{"game_id": "a57ae15b-1404-4432-91d2-4325bfb1dd53", "score": 100, "timestamp": "2026-03-18T13:35:22.480695", "row": 1, "column": 1, "message": "Game started with specified height and width.", "height": 10, "width": 10, "type": "GameStartedEvent"}
{"game_id": "a57ae15b-1404-4432-91d2-4325bfb1dd53", "score": 99, "timestamp": "2026-03-18T13:35:23.852166", "row": 0, "column": 1, "message": "You moved in the specified direction.", "direction": "N", "type": "PlayerMovedEvent"}
{"game_id": "a57ae15b-1404-4432-91d2-4325bfb1dd53", "score": 198, "timestamp": "2026-03-18T13:35:24.640758", "row": 0, "column": 2, "message": "You found the exit at specified height and width!", "type": "ExitFoundEvent"}
{"game_id": "1c1fa685-5672-4a10-b68a-cb9a51925b69", "score": 100, "timestamp": "2026-03-18T13:35:25.552576", "row": 9, "column": 5, "message": "Game started with specified height and width.", "height": 10, "width": 10, "type": "GameStartedEvent"}
{"game_id": "1c1fa685-5672-4a10-b68a-cb9a51925b69", "score": 89, "timestamp": "2026-03-18T13:35:26.484042", "row": 9, "column": 5, "direction": "S", "message": "You are at the end of the board.", "type": "MoveFailedEvent"}
{"game_id": "1c1fa685-5672-4a10-b68a-cb9a51925b69", "score": 88, "timestamp": "2026-03-18T13:35:27.653440", "row": 9, "column": 6, "message": "You moved in the specified direction.", "direction": "E", "type": "PlayerMovedEvent"}
{"game_id": "1c1fa685-5672-4a10-b68a-cb9a51925b69", "score": 87, "timestamp": "2026-03-18T13:35:28.751121", "row": 9, "column": 7, "message": "You moved in the specified direction.", "direction": "E", "type": "PlayerMovedEvent"}
{"game_id": "1c1fa685-5672-4a10-b68a-cb9a51925b69", "score": 86, "timestamp": "2026-03-18T13:35:30.128800", "row": 8, "column": 7, "message": "You moved in the specified direction.", "direction": "N", "type": "PlayerMovedEvent"}
{"game_id": "1c1fa685-5672-4a10-b68a-cb9a51925b69", "score": 84, "timestamp": "2026-03-18T13:35:30.692810", "row": 7, "column": 7, "character_message": "You hit a wall!", "points": -1, "type": "CharacterFoundEvent"}
{"game_id": "1c1fa685-5672-4a10-b68a-cb9a51925b69", "score": 83, "timestamp": "2026-03-18T13:35:31.699545", "row": 6, "column": 7, "message": "You moved in the specified direction.", "direction": "N", "type": "PlayerMovedEvent"}
{"game_id": "1c1fa685-5672-4a10-b68a-cb9a51925b69", "score": 182, "timestamp": "2026-03-18T13:35:32.624537", "row": 5, "column": 7, "message": "You found the exit at specified height and width!", "type": "ExitFoundEvent"}
{"game_id": "23b3dd75-d233-4fb5-9a85-54f8bbbed085", "score": 100, "timestamp": "2026-03-18T13:35:33.493263", "row": 9, "column": 8, "message": "Game started with specified height and width.", "height": 10, "width": 10, "type": "GameStartedEvent"}
{"game_id": "23b3dd75-d233-4fb5-9a85-54f8bbbed085", "score": 99, "timestamp": "2026-03-18T13:35:35.838145", "row": 9, "column": 9, "message": "You moved in the specified direction.", "direction": "E", "type": "PlayerMovedEvent"}
{"game_id": "23b3dd75-d233-4fb5-9a85-54f8bbbed085", "score": 98, "timestamp": "2026-03-18T13:35:37.327890", "row": 9, "column": 8, "message": "You moved in the specified direction.", "direction": "W", "type": "PlayerMovedEvent"}
{"game_id": "23b3dd75-d233-4fb5-9a85-54f8bbbed085", "score": 97, "timestamp": "2026-03-18T13:35:39.326379", "row": 9, "column": 7, "message": "You moved in the specified direction.", "direction": "W", "type": "PlayerMovedEvent"}
{"game_id": "23b3dd75-d233-4fb5-9a85-54f8bbbed085", "score": 96, "timestamp": "2026-03-18T13:35:40.342838", "row": 9, "column": 6, "message": "You moved in the specified direction.", "direction": "W", "type": "PlayerMovedEvent"}
{"game_id": "23b3dd75-d233-4fb5-9a85-54f8bbbed085", "score": 95, "timestamp": "2026-03-18T13:35:41.036227", "row": 8, "column": 6, "message": "You moved in the specified direction.", "direction": "N", "type": "PlayerMovedEvent"}
{"game_id": "23b3dd75-d233-4fb5-9a85-54f8bbbed085", "score": 94, "timestamp": "2026-03-18T13:35:41.443272", "row": 7, "column": 6, "message": "You moved in the specified direction.", "direction": "N", "type": "PlayerMovedEvent"}
{"game_id": "23b3dd75-d233-4fb5-9a85-54f8bbbed085", "score": 193, "timestamp": "2026-03-18T13:35:41.827945", "row": 6, "column": 6, "message": "You found the exit at specified height and width!", "type": "ExitFoundEvent"}
{"game_id": "2fbcc5e5-a7a0-4aaa-9368-07d88344a0e3", "score": 100, "timestamp": "2026-03-18T13:35:42.639750", "row": 6, "column": 2, "message": "Game started with specified height and width.", "height": 10, "width": 10, "type": "GameStartedEvent"}
{"game_id": "2fbcc5e5-a7a0-4aaa-9368-07d88344a0e3", "score": 99, "timestamp": "2026-03-18T13:35:43.670342", "row": 5, "column": 2, "message": "You moved in the specified direction.", "direction": "N", "type": "PlayerMovedEvent"}
{"game_id": "2fbcc5e5-a7a0-4aaa-9368-07d88344a0e3", "score": 98, "timestamp": "2026-03-18T13:35:45.518177", "row": 6, "column": 2, "message": "You moved in the specified direction.", "direction": "S", "type": "PlayerMovedEvent"}
{"game_id": "2fbcc5e5-a7a0-4aaa-9368-07d88344a0e3", "score": 97, "timestamp": "2026-03-18T13:35:45.991833", "row": 7, "column": 2, "message": "You moved in the specified direction.", "direction": "S", "type": "PlayerMovedEvent"}
{"game_id": "2fbcc5e5-a7a0-4aaa-9368-07d88344a0e3", "score": 96, "timestamp": "2026-03-18T13:35:46.301885", "row": 8, "column": 2, "message": "You moved in the specified direction.", "direction": "S", "type": "PlayerMovedEvent"}
{"game_id": "2fbcc5e5-a7a0-4aaa-9368-07d88344a0e3", "score": 95, "timestamp": "2026-03-18T13:35:46.574582", "row": 9, "column": 2, "message": "You moved in the specified direction.", "direction": "S", "type": "PlayerMovedEvent"}
{"game_id": "2fbcc5e5-a7a0-4aaa-9368-07d88344a0e3", "score": 84, "timestamp": "2026-03-18T13:35:46.822862", "row": 9, "column": 2, "direction": "S", "message": "You are at the end of the board.", "type": "MoveFailedEvent"}
{"game_id": "2fbcc5e5-a7a0-4aaa-9368-07d88344a0e3", "score": 73, "timestamp": "2026-03-18T13:35:47.025811", "row": 9, "column": 2, "direction": "S", "message": "You are at the end of the board.", "type": "MoveFailedEvent"}
{"game_id": "2fbcc5e5-a7a0-4aaa-9368-07d88344a0e3", "score": 72, "timestamp": "2026-03-18T13:35:48.440411", "row": 9, "column": 3, "message": "You moved in the specified direction.", "direction": "E", "type": "PlayerMovedEvent"}
{"game_id": "2fbcc5e5-a7a0-4aaa-9368-07d88344a0e3", "score": 71, "timestamp": "2026-03-18T13:35:49.320134", "row": 9, "column": 4, "message": "You moved in the specified direction.", "direction": "E", "type": "PlayerMovedEvent"}
{"game_id": "2fbcc5e5-a7a0-4aaa-9368-07d88344a0e3", "score": 70, "timestamp": "2026-03-18T13:35:49.631184", "row": 9, "column": 5, "message": "You moved in the specified direction.", "direction": "E", "type": "PlayerMovedEvent"}
{"game_id": "2fbcc5e5-a7a0-4aaa-9368-07d88344a0e3", "score": 69, "timestamp": "2026-03-18T13:35:49.927730", "row": 9, "column": 6, "message": "You moved in the specified direction.", "direction": "E", "type": "PlayerMovedEvent"}
{"game_id": "2fbcc5e5-a7a0-4aaa-9368-07d88344a0e3", "score": 68, "timestamp": "2026-03-18T13:35:50.197738", "row": 9, "column": 7, "message": "You moved in the specified direction.", "direction": "E", "type": "PlayerMovedEvent"}
{"game_id": "2fbcc5e5-a7a0-4aaa-9368-07d88344a0e3", "score": 67, "timestamp": "2026-03-18T13:35:50.468058", "row": 9, "column": 8, "message": "You moved in the specified direction.", "direction": "E", "type": "PlayerMovedEvent"}
{"game_id": "2fbcc5e5-a7a0-4aaa-9368-07d88344a0e3", "score": 65, "timestamp": "2026-03-18T13:35:50.737784", "row": 9, "column": 9, "character_message": "You hit a monster!", "points": -1, "type": "CharacterFoundEvent"}
{"game_id": "2fbcc5e5-a7a0-4aaa-9368-07d88344a0e3", "score": 54, "timestamp": "2026-03-18T13:35:50.986189", "row": 9, "column": 9, "direction": "E", "message": "You are at the end of the board.", "type": "MoveFailedEvent"}
{"game_id": "2fbcc5e5-a7a0-4aaa-9368-07d88344a0e3", "score": 43, "timestamp": "2026-03-18T13:35:53.460489", "row": 9, "column": 9, "direction": "E", "message": "You are at the end of the board.", "type": "MoveFailedEvent"}
{"game_id": "2fbcc5e5-a7a0-4aaa-9368-07d88344a0e3", "score": 42, "timestamp": "2026-03-18T13:35:55.055410", "row": 8, "column": 9, "message": "You moved in the specified direction.", "direction": "N", "type": "PlayerMovedEvent"}
{"game_id": "2fbcc5e5-a7a0-4aaa-9368-07d88344a0e3", "score": 41, "timestamp": "2026-03-18T13:35:55.284104", "row": 7, "column": 9, "message": "You moved in the specified direction.", "direction": "N", "type": "PlayerMovedEvent"}
{"game_id": "2fbcc5e5-a7a0-4aaa-9368-07d88344a0e3", "score": 40, "timestamp": "2026-03-18T13:35:55.507795", "row": 6, "column": 9, "message": "You moved in the specified direction.", "direction": "N", "type": "PlayerMovedEvent"}
{"game_id": "2fbcc5e5-a7a0-4aaa-9368-07d88344a0e3", "score": 39, "timestamp": "2026-03-18T13:35:55.711107", "row": 5, "column": 9, "message": "You moved in the specified direction.", "direction": "N", "type": "PlayerMovedEvent"}
{"game_id": "2fbcc5e5-a7a0-4aaa-9368-07d88344a0e3", "score": 38, "timestamp": "2026-03-18T13:35:55.936003", "row": 4, "column": 9, "message": "You moved in the specified direction.", "direction": "N", "type": "PlayerMovedEvent"}
{"game_id": "2fbcc5e5-a7a0-4aaa-9368-07d88344a0e3", "score": 37, "timestamp": "2026-03-18T13:35:57.376909", "row": 3, "column": 9, "message": "You moved in the specified direction.", "direction": "N", "type": "PlayerMovedEvent"}
{"game_id": "2fbcc5e5-a7a0-4aaa-9368-07d88344a0e3", "score": 41, "timestamp": "2026-03-18T13:35:57.692482", "row": 2, "column": 9, "character_message": "You found a gem", "points": 5, "type": "CharacterFoundEvent"}
{"game_id": "2fbcc5e5-a7a0-4aaa-9368-07d88344a0e3", "score": 40, "timestamp": "2026-03-18T13:35:57.963506", "row": 1, "column": 9, "message": "You moved in the specified direction.", "direction": "N", "type": "PlayerMovedEvent"}
{"game_id": "2fbcc5e5-a7a0-4aaa-9368-07d88344a0e3", "score": 39, "timestamp": "2026-03-18T13:35:58.995946", "row": 0, "column": 9, "message": "You moved in the specified direction.", "direction": "N", "type": "PlayerMovedEvent"}
{"game_id": "2fbcc5e5-a7a0-4aaa-9368-07d88344a0e3", "score": 28, "timestamp": "2026-03-18T13:35:59.535736", "row": 0, "column": 9, "direction": "N", "message": "You are at the end of the board.", "type": "MoveFailedEvent"}
{"game_id": "2fbcc5e5-a7a0-4aaa-9368-07d88344a0e3", "score": 27, "timestamp": "2026-03-18T13:36:01.448613", "row": 0, "column": 8, "message": "You moved in the specified direction.", "direction": "W", "type": "PlayerMovedEvent"}
{"game_id": "2fbcc5e5-a7a0-4aaa-9368-07d88344a0e3", "score": 26, "timestamp": "2026-03-18T13:36:02.168894", "row": 0, "column": 7, "message": "You moved in the specified direction.", "direction": "W", "type": "PlayerMovedEvent"}
{"game_id": "2fbcc5e5-a7a0-4aaa-9368-07d88344a0e3", "score": 25, "timestamp": "2026-03-18T13:36:02.482621", "row": 0, "column": 6, "message": "You moved in the specified direction.", "direction": "W", "type": "PlayerMovedEvent"}
{"game_id": "2fbcc5e5-a7a0-4aaa-9368-07d88344a0e3", "score": 24, "timestamp": "2026-03-18T13:36:03.337559", "row": 0, "column": 5, "message": "You moved in the specified direction.", "direction": "W", "type": "PlayerMovedEvent"}
{"game_id": "2fbcc5e5-a7a0-4aaa-9368-07d88344a0e3", "score": 23, "timestamp": "2026-03-18T13:36:03.716161", "row": 1, "column": 5, "message": "You moved in the specified direction.", "direction": "S", "type": "PlayerMovedEvent"}
{"game_id": "2fbcc5e5-a7a0-4aaa-9368-07d88344a0e3", "score": 22, "timestamp": "2026-03-18T13:36:04.125551", "row": 1, "column": 4, "message": "You moved in the specified direction.", "direction": "W", "type": "PlayerMovedEvent"}
{"game_id": "2fbcc5e5-a7a0-4aaa-9368-07d88344a0e3", "score": 21, "timestamp": "2026-03-18T13:36:04.732791", "row": 2, "column": 4, "message": "You moved in the specified direction.", "direction": "S", "type": "PlayerMovedEvent"}
{"game_id": "2fbcc5e5-a7a0-4aaa-9368-07d88344a0e3", "score": 20, "timestamp": "2026-03-18T13:36:05.225904", "row": 3, "column": 4, "message": "You moved in the specified direction.", "direction": "S", "type": "PlayerMovedEvent"}
{"game_id": "2fbcc5e5-a7a0-4aaa-9368-07d88344a0e3", "score": 19, "timestamp": "2026-03-18T13:36:05.651582", "row": 4, "column": 4, "message": "You moved in the specified direction.", "direction": "S", "type": "PlayerMovedEvent"}
{"game_id": "2fbcc5e5-a7a0-4aaa-9368-07d88344a0e3", "score": 18, "timestamp": "2026-03-18T13:36:06.151977", "row": 5, "column": 4, "message": "You moved in the specified direction.", "direction": "S", "type": "PlayerMovedEvent"}
{"game_id": "2fbcc5e5-a7a0-4aaa-9368-07d88344a0e3", "score": 117, "timestamp": "2026-03-18T13:36:08.105756", "row": 5, "column": 3, "message": "You found the exit at specified height and width!", "type": "ExitFoundEvent"}
